[
	{
		"id": 1401,
		"name": "赤王陵",
		"Price": 100000,
		"one": [
			{
				"id": 1410001,
				"name": "赤王陵的一角沙子",
				"class": "道具",
				"type": "活动秘境道具",
				"desc": "1.4版本活动道具",
				"出售价": 1
			},
			{
				"id": 200202,
				"name": "2w",
				"class": "道具",
				"type": "钞票",
				"desc": "存储",
				"出售价": 20000
			},
			{
				"id": 20000053,
				"name": "摘榜令",
				"class": "道具",
				"type": "比试",
				"desc": "增加挑战次数(次数为0时自动使用)",
				"出售价": 288888
			},
			{
				"id": 20000053,
				"name": "秘境之匙",
				"class": "道具",
				"type": "秘境",
				"desc": "打开沉迷的大门",
				"出售价": 1
			}
		],
		"two": [
			{
				"name": "冰封迷途",
				"class": "装备",
				"type": "项链",
				"属性": "冰",
				"加成": 0.2
			},
			{
				"name": "翠绿之影",
				"class": "装备",
				"type": "项链",
				"属性": "风",
				"加成": 0.2
			},
			{
				"name": "如雷盛怒",
				"class": "装备",
				"type": "项链",
				"属性": "雷",
				"加成": 0.2
			},
			{
				"name": "炽烈魔炎",
				"class": "装备",
				"type": "项链",
				"属性": "火",
				"加成": 0.2
			},
			{
				"name": "沉沦之心",
				"class": "装备",
				"type": "项链",
				"属性": "水",
				"加成": 0.2
			},
			{
				"name": "深林的记忆",
				"class": "装备",
				"type": "项链",
				"属性": "木",
				"加成": 0.2
			},
			{
				"name": "悠古的磐岩",
				"class": "装备",
				"type": "项链",
				"属性": "岩",
				"加成": 0.2
			}
		],
		"three": [
			{
				"id": 1410002,
				"name": "赤王陵的石板",
				"class": "道具",
				"type": "活动秘境道具",
				"desc": "1.4版本活动道具",
				"出售价": 1
			},
			{
				"id": 80009,
				"name": "岩浆",
				"class": "材料",
				"type": "稀有",
				"desc": "一桶火滚滚的岩浆",
				"出售价": 3000000
			}
		]
	},
	{
		"id": 1402,
		"name": "永冬岭",
		"Price": 500000,
		"one": [
			{
				"id": 200202,
				"name": "2w",
				"class": "道具",
				"type": "钞票",
				"desc": "存储",
				"出售价": 20000
			},
			{
				"id": 20000053,
				"name": "摘榜令",
				"class": "道具",
				"type": "比试",
				"desc": "增加挑战次数(次数为0时自动使用)",
				"出售价": 288888
			},
			{
				"id": 20000053,
				"name": "秘境之匙",
				"class": "道具",
				"type": "秘境",
				"desc": "打开沉迷的大门",
				"出售价": 1
			}
		],
		"two": [
			{
				"name": "冰封迷途",
				"class": "装备",
				"type": "项链",
				"属性": "冰",
				"加成": 0.2
			},
			{
				"name": "翠绿之影",
				"class": "装备",
				"type": "项链",
				"属性": "风",
				"加成": 0.2
			},
			{
				"name": "如雷盛怒",
				"class": "装备",
				"type": "项链",
				"属性": "雷",
				"加成": 0.2
			},
			{
				"name": "炽烈魔炎",
				"class": "装备",
				"type": "项链",
				"属性": "火",
				"加成": 0.2
			},
			{
				"name": "沉沦之心",
				"class": "装备",
				"type": "项链",
				"属性": "水",
				"加成": 0.2
			},
			{
				"name": "深林的记忆",
				"class": "装备",
				"type": "项链",
				"属性": "木",
				"加成": 0.2
			},
			{
				"name": "悠古的磐岩",
				"class": "装备",
				"type": "项链",
				"属性": "岩",
				"加成": 0.2
			}
		],
		"three": [
			{
				"id": 200010001,
				"name": "守护的碎片",
				"class": "道具",
				"type": "遗迹道具",
				"desc": "遗迹道具",
				"出售价": 1
			},
			{
				"id": 80009,
				"name": "岩浆",
				"class": "材料",
				"type": "稀有",
				"desc": "一桶火滚滚的岩浆",
				"出售价": 3000000
			}
		]
	}
]